graphql_sync_dataloaders/__init__.py
graphql_sync_dataloaders/exceptions.py
graphql_sync_dataloaders/execution_context.py
graphql_sync_dataloaders/sync_dataloader.py
graphql_sync_dataloaders/sync_future.py
graphql_sync_dataloaders-0.1.1.dist-info/LICENSE
graphql_sync_dataloaders-0.1.1.dist-info/WHEEL
graphql_sync_dataloaders-0.1.1.dist-info/METADATA
graphql_sync_dataloaders-0.1.1.dist-info/RECORD
