Metadata-Version: 2.1
Name: graphql-sync-dataloaders
Version: 0.1.1
Summary: Use DataLoaders in your Python GraphQL servers that have to run in a sync context (i.e. Django).
Home-page: https://github.com/jkimbo/graphql-sync-dataloaders
License: MIT
Keywords: graphql,Django,strawberry-graphql
Author: Jonathan Kim
Author-email: hello@jkimbo.com
Requires-Python: >=3.8,<4.0
Classifier: Intended Audience :: Developers
Classifier: License :: OSI Approved :: MIT License
Classifier: Programming Language :: Python :: 3
Classifier: Programming Language :: Python :: 3.8
Classifier: Programming Language :: Python :: 3.9
Classifier: Programming Language :: Python :: 3.10
Classifier: Programming Language :: Python :: 3
Classifier: Topic :: Software Development :: Libraries
Classifier: Topic :: Software Development :: Libraries :: Python Modules
Requires-Dist: graphql-core (>=3.2.0,<3.3.0)
Project-URL: Repository, https://github.com/jkimbo/graphql-sync-dataloaders
